LICENSE
MANIFEST.in
README.rst
setup.py
zbx_dashboard/__init__.py
zbx_dashboard/admin.py
zbx_dashboard/apps.py
zbx_dashboard/forms.py
zbx_dashboard/models.py
zbx_dashboard/tests.py
zbx_dashboard/urls.py
zbx_dashboard/utils.py
zbx_dashboard/views.py
zbx_dashboard.egg-info/PKG-INFO
zbx_dashboard.egg-info/SOURCES.txt
zbx_dashboard.egg-info/dependency_links.txt
zbx_dashboard.egg-info/requires.txt
zbx_dashboard.egg-info/top_level.txt
zbx_dashboard/locale/ru/LC_MESSAGES/django.mo
zbx_dashboard/locale/ru/LC_MESSAGES/django.po
zbx_dashboard/static/zbx_dashboard/css/bootstrap-theme.css
zbx_dashboard/static/zbx_dashboard/css/bootstrap-theme.css.map
zbx_dashboard/static/zbx_dashboard/css/bootstrap-theme.min.css
zbx_dashboard/static/zbx_dashboard/css/bootstrap.css
zbx_dashboard/static/zbx_dashboard/css/bootstrap.css.map
zbx_dashboard/static/zbx_dashboard/css/bootstrap.min.css
zbx_dashboard/static/zbx_dashboard/fonts/glyphicons-halflings-regular.eot
zbx_dashboard/static/zbx_dashboard/fonts/glyphicons-halflings-regular.svg
zbx_dashboard/static/zbx_dashboard/fonts/glyphicons-halflings-regular.ttf
zbx_dashboard/static/zbx_dashboard/fonts/glyphicons-halflings-regular.woff
zbx_dashboard/static/zbx_dashboard/js/bootstrap.js
zbx_dashboard/static/zbx_dashboard/js/bootstrap.min.js
zbx_dashboard/static/zbx_dashboard/js/jquery-1.11.1.js
zbx_dashboard/static/zbx_dashboard/js/jquery-ui.js
zbx_dashboard/static/zbx_dashboard/js/jquery.cookie.js
zbx_dashboard/static/zbx_dashboard/js/jquery.formset.js
zbx_dashboard/templates/404.html
zbx_dashboard/templates/registration/logged_out.html
zbx_dashboard/templates/registration/login.html
zbx_dashboard/templates/zbx_dashboard/add.html
zbx_dashboard/templates/zbx_dashboard/base.html
zbx_dashboard/templates/zbx_dashboard/detail.html
zbx_dashboard/templates/zbx_dashboard/list.html
zbx_dashboard/templates/zbx_dashboard/update.html
zbx_dashboard/templatetags/__init__.py
zbx_dashboard/templatetags/__init__.pyc
zbx_dashboard/templatetags/pass_period.py
zbx_dashboard/templatetags/pass_period.pyc