Metadata-Version: 1.1
Name: zbx-dashboard
Version: 0.1.2
Summary: Simple Django applicattion that provides an alternative to the Zabbix screens.
Home-page: https://github.com/banzayats/zbx-dashboard/
Author: Vadym Kalsin
Author-email: neformat@gmail.com
License: MIT
Platform: UNKNOWN
Classifier: Environment :: Web Environment
Classifier: Framework :: Django
Classifier: Intended Audience :: Developers
Classifier: Intended Audience :: Information Technology
Classifier: Intended Audience :: System Administrators
Classifier: License :: OSI Approved :: MIT License
Classifier: Operating System :: OS Independent
Classifier: Programming Language :: Python
Classifier: Programming Language :: Python :: 2.6
Classifier: Programming Language :: Python :: 2.7
Classifier: Topic :: Internet :: WWW/HTTP
Classifier: Topic :: System :: Monitoring
